jupyterlite_xeus_sqlite/__init__.py
jupyterlite_xeus_sqlite/_version.py
jupyterlite_xeus_sqlite/labextension/package.json
jupyterlite_xeus_sqlite/labextension/static/1d294d21c80c4bf4e239740688a0c5b9d5b34ce1d8bc7749901c022b22be74fb.png
jupyterlite_xeus_sqlite/labextension/static/213.8aaac7ad731027476a9d.js
jupyterlite_xeus_sqlite/labextension/static/747.10a6f744ae4fc802a94c.js
jupyterlite_xeus_sqlite/labextension/static/895.7cb441ab57069eb8f09d.js
jupyterlite_xeus_sqlite/labextension/static/e58e163d9cee25f19e1d4586ccd4799e79e59128faa463177e9cfd9d2ab4459f.png
jupyterlite_xeus_sqlite/labextension/static/remoteEntry.098ba362c471964915fd.js
jupyterlite_xeus_sqlite/labextension/static/style.js
jupyterlite_xeus_sqlite/labextension/static/third-party-licenses.json
jupyterlite_xeus_sqlite/labextension/static/xeus_kernel.wasm
jupyterlite_xeus_sqlite-0.2.0.data/data/share/jupyter/labextensions/jupyterlite-xeus-sqlite/install.json
jupyterlite_xeus_sqlite-0.2.0.data/data/share/jupyter/labextensions/jupyterlite-xeus-sqlite/package.json
jupyterlite_xeus_sqlite-0.2.0.data/data/share/jupyter/labextensions/jupyterlite-xeus-sqlite/static/1d294d21c80c4bf4e239740688a0c5b9d5b34ce1d8bc7749901c022b22be74fb.png
jupyterlite_xeus_sqlite-0.2.0.data/data/share/jupyter/labextensions/jupyterlite-xeus-sqlite/static/213.8aaac7ad731027476a9d.js
jupyterlite_xeus_sqlite-0.2.0.data/data/share/jupyter/labextensions/jupyterlite-xeus-sqlite/static/747.10a6f744ae4fc802a94c.js
jupyterlite_xeus_sqlite-0.2.0.data/data/share/jupyter/labextensions/jupyterlite-xeus-sqlite/static/895.7cb441ab57069eb8f09d.js
jupyterlite_xeus_sqlite-0.2.0.data/data/share/jupyter/labextensions/jupyterlite-xeus-sqlite/static/e58e163d9cee25f19e1d4586ccd4799e79e59128faa463177e9cfd9d2ab4459f.png
jupyterlite_xeus_sqlite-0.2.0.data/data/share/jupyter/labextensions/jupyterlite-xeus-sqlite/static/remoteEntry.098ba362c471964915fd.js
jupyterlite_xeus_sqlite-0.2.0.data/data/share/jupyter/labextensions/jupyterlite-xeus-sqlite/static/style.js
jupyterlite_xeus_sqlite-0.2.0.dist-info/LICENSE
jupyterlite_xeus_sqlite-0.2.0.dist-info/METADATA
jupyterlite_xeus_sqlite-0.2.0.dist-info/WHEEL
jupyterlite_xeus_sqlite-0.2.0.dist-info/top_level.txt
jupyterlite_xeus_sqlite-0.2.0.dist-info/RECORD
